ros2_calib/__init__.py
ros2_calib/bag_handler.py
ros2_calib/calibration.py
ros2_calib/calibration_widget.py
ros2_calib/common.py
ros2_calib/dual_calibration_widget.py
ros2_calib/frame_selection_widget.py
ros2_calib/lidar2lidar_o3d_widget.py
ros2_calib/lidar_cleaner.py
ros2_calib/main.py
ros2_calib/main_window.py
ros2_calib/ros_utils.py
ros2_calib/tf_graph_widget.py
ros2_calib/tf_transformations.py
ros2_calib-0.1.1.dist-info/licenses/LICENSE
ros2_calib-0.1.1.dist-info/METADATA
ros2_calib-0.1.1.dist-info/WHEEL
ros2_calib-0.1.1.dist-info/entry_points.txt
ros2_calib-0.1.1.dist-info/top_level.txt
ros2_calib-0.1.1.dist-info/RECORD
