Metadata-Version: 2.4
Name: ros2-calib
Version: 0.1.1
Summary: A manual LiDAR-Camera calibration tool for ROS 2
Author-email: Till Beemelmanns <till.beemelmanns@rwth-aachen.de>
Maintainer-email: Till Beemelmanns <till.beemelmanns@rwth-aachen.de>
License-Expression: MIT
Project-URL: Homepage, https://github.com/beemelmanns/ros2_calib
Project-URL: Repository, https://github.com/beemelmanns/ros2_calib
Project-URL: Issues, https://github.com/beemelmanns/ros2_calib/issues
Keywords: ros2,lidar,camera,calibration,robotics,computer-vision
Classifier: Development Status :: 4 - Beta
Classifier: Intended Audience :: Science/Research
Classifier: Intended Audience :: Developers
Classifier: Operating System :: OS Independent
Classifier: Programming Language :: Python :: 3
Classifier: Programming Language :: Python :: 3.8
Classifier: Programming Language :: Python :: 3.9
Classifier: Programming Language :: Python :: 3.10
Classifier: Programming Language :: Python :: 3.11
Classifier: Topic :: Scientific/Engineering :: Artificial Intelligence
Classifier: Topic :: Scientific/Engineering :: Image Processing
Classifier: Topic :: Software Development :: Libraries :: Python Modules
Requires-Python: >=3.8
License-File: LICENSE
Requires-Dist: rosbags
Requires-Dist: numpy
Requires-Dist: PySide6
Requires-Dist: opencv-python-headless
Requires-Dist: scipy
Requires-Dist: NodeGraphQt
Requires-Dist: transforms3d
Requires-Dist: setuptools
Requires-Dist: open3d
Provides-Extra: dev
Requires-Dist: ruff; extra == "dev"
Requires-Dist: build; extra == "dev"
Requires-Dist: twine; extra == "dev"
Dynamic: license-file
